Metadata-Version: 1.2
Name: xrviz
Version: 0.1.4
Summary: Interactive visualisations for xarrays
Home-page: UNKNOWN
Maintainer: Martin Durant
Maintainer-email: mdurant@anaconda.com
License: BSD
Platform: UNKNOWN
